enda/__init__.py
enda/backtesting.py
enda/config.py
enda/contracts.py
enda/estimators.py
enda/feature_engineering/__init__.py
enda/feature_engineering/calendar.py
enda/feature_engineering/datetime_features.py
enda/ml_backends/__init__.py
enda/ml_backends/h2o_estimator.py
enda/ml_backends/sklearn_estimator.py
enda/power_predictor.py
enda/power_stations.py
enda/scoring.py
enda/timeseries.py
enda/timezone_utils.py
enda/tools/__init__.py
enda/tools/decorators.py
enda/tools/portfolio_tools.py
enda/tools/resample.py
enda/tools/timeseries.py
enda/tools/timezone_utils.py
enda-1.0.5.dist-info/METADATA
enda-1.0.5.dist-info/WHEEL
enda-1.0.5.dist-info/licenses/LICENSE
enda-1.0.5.dist-info/licenses/LICENSES/LICENSE_DATEUTIL
enda-1.0.5.dist-info/licenses/LICENSES/LICENSE_NUMPY
enda-1.0.5.dist-info/licenses/LICENSES/LICENSE_PANDAS
enda-1.0.5.dist-info/licenses/LICENSES/LICENSE_PYTZ
enda-1.0.5.dist-info/RECORD
