Metadata-Version: 2.4
Name: enda
Version: 1.0.5
Summary: Tools to manipulate energy time-series and contracts, and to perform forecasts.
License-Expression: MIT
License-File: LICENSE
License-File: LICENSES/LICENSE_DATEUTIL
License-File: LICENSES/LICENSE_NUMPY
License-File: LICENSES/LICENSE_PANDAS
License-File: LICENSES/LICENSE_PYTZ
Author: Enercoop
Author-email: team-data@enercoop.org
Requires-Python: ~=3.9
Classifier: Programming Language :: Python :: 3
Classifier: Operating System :: OS Independent
Provides-Extra: dev
Provides-Extra: examples
Requires-Dist: black ; extra == "dev"
Requires-Dist: coverage ; extra == "dev"
Requires-Dist: datatable (>=1.1,<2.0)
Requires-Dist: h2o (>=3.38,<4.0)
Requires-Dist: ipykernel ; extra == "dev"
Requires-Dist: joblib ; extra == "examples"
Requires-Dist: jours-feries-france (>=0.7.0,<0.8.0)
Requires-Dist: jupyter ; extra == "examples"
Requires-Dist: matplotlib ; extra == "examples"
Requires-Dist: numexpr ; extra == "examples"
Requires-Dist: numpy (>=1.18,<2.0)
Requires-Dist: pandas (>=1.4.0,<2.0.0)
Requires-Dist: polars (>=0.20,<1.0)
Requires-Dist: pre-commit ; extra == "dev"
Requires-Dist: pylint ; extra == "dev"
Requires-Dist: scikit-learn (>=1.0,<2.0)
Requires-Dist: seaborn ; extra == "examples"
Requires-Dist: setuptools ; extra == "dev"
Requires-Dist: statsmodels (<=0.13.5)
Requires-Dist: tox ; extra == "dev"
Requires-Dist: twine ; extra == "dev"
Requires-Dist: unidecode (>=1.3,<2.0)
Requires-Dist: vacances-scolaires-france (>=0.11,<1.0)
Requires-Dist: wheel ; extra == "dev"
Project-URL: Bug Tracker, https://github.com/enercoop/enda/issues
